python_optimizer/__init__.py
python_optimizer/cli.py
python_optimizer/specialization_cache.py
python_optimizer/benchmarks/test_jit_performance.py
python_optimizer/core/__init__.py
python_optimizer/core/decorator.py
python_optimizer/core/engine.py
python_optimizer/distributed/__init__.py
python_optimizer/distributed/backend.py
python_optimizer/distributed/coordinator.py
python_optimizer/distributed/decorator.py
python_optimizer/distributed/genetic.py
python_optimizer/distributed/jit_cache.py
python_optimizer/distributed/spec_cache.py
python_optimizer/distributed/worker.py
python_optimizer/genetic/__init__.py
python_optimizer/genetic/genetic_optimizer.py
python_optimizer/gpu/__init__.py
python_optimizer/gpu/device.py
python_optimizer/gpu/dispatcher.py
python_optimizer/gpu/genetic.py
python_optimizer/gpu/kernels.py
python_optimizer/gpu/memory.py
python_optimizer/jit/__init__.py
python_optimizer/jit/jit_fitness_evaluator.py
python_optimizer/ml/__init__.py
python_optimizer/ml/pytorch_optimizer.py
python_optimizer/ml/tensorflow_optimizer.py
python_optimizer/profiling/__init__.py
python_optimizer/profiling/advanced_profiler.py
python_optimizer/profiling/profiler.py
python_optimizer/specialization/__init__.py
python_optimizer/specialization/analyzer.py
python_optimizer/specialization/cache.py
python_optimizer/specialization/dispatcher.py
python_optimizer/specialization/engine.py
python_optimizer/specialization/generators.py
python_optimizer-1.1.0.dist-info/METADATA
python_optimizer-1.1.0.dist-info/WHEEL
python_optimizer-1.1.0.dist-info/entry_points.txt
python_optimizer-1.1.0.dist-info/licenses/LICENSE
python_optimizer-1.1.0.dist-info/RECORD
