Metadata-Version: 2.4
Name: python-optimizer
Version: 1.1.0
Summary: High-performance Python optimization toolkit with JIT compilation, variable specialization, and runtime optimizations
Project-URL: Homepage, https://github.com/thinmanj/python-optimizer
Project-URL: Documentation, https://python-optimizer.readthedocs.io
Project-URL: Repository, https://github.com/thinmanj/python-optimizer.git
Project-URL: Issues, https://github.com/thinmanj/python-optimizer/issues
Project-URL: Changelog, https://github.com/thinmanj/python-optimizer/blob/main/CHANGELOG.md
Author-email: Julio Ona <thinmanj@gmail.com>
Maintainer-email: Julio Ona <thinmanj@gmail.com>
License: MIT
License-File: LICENSE
Keywords: acceleration,compiler,financial-computing,genetic-algorithm,jit,numba,optimization,performance,python,trading
Classifier: Development Status :: 4 - Beta
Classifier: Intended Audience :: Developers
Classifier: Intended Audience :: Financial and Insurance Industry
Classifier: Intended Audience :: Science/Research
Classifier: License :: OSI Approved :: MIT License
Classifier: Operating System :: OS Independent
Classifier: Programming Language :: Python :: 3
Classifier: Programming Language :: Python :: 3.11
Classifier: Programming Language :: Python :: 3.12
Classifier: Programming Language :: Python :: 3.13
Classifier: Topic :: Office/Business :: Financial :: Investment
Classifier: Topic :: Scientific/Engineering
Classifier: Topic :: Software Development :: Compilers
Classifier: Topic :: Software Development :: Libraries :: Python Modules
Classifier: Topic :: System :: Benchmark
Requires-Python: >=3.11
Requires-Dist: matplotlib>=3.7.0
Requires-Dist: numba>=0.58.0
Requires-Dist: numpy>=1.24.0
Requires-Dist: pandas>=2.0.0
Requires-Dist: pydantic>=2.0.0
Requires-Dist: scipy>=1.10.0
Requires-Dist: toml>=0.10.0
Requires-Dist: tqdm>=4.65.0
Provides-Extra: all
Requires-Dist: black>=23.0.0; extra == 'all'
Requires-Dist: cupy-cuda12x>=12.0.0; extra == 'all'
Requires-Dist: flake8>=6.0.0; extra == 'all'
Requires-Dist: isort>=5.12.0; extra == 'all'
Requires-Dist: mypy>=1.5.0; extra == 'all'
Requires-Dist: nbsphinx>=0.9.0; extra == 'all'
Requires-Dist: numba[cuda]>=0.58.0; extra == 'all'
Requires-Dist: optuna>=3.3.0; extra == 'all'
Requires-Dist: pre-commit>=3.3.0; extra == 'all'
Requires-Dist: pytest-benchmark>=4.0.0; extra == 'all'
Requires-Dist: pytest-cov>=4.1.0; extra == 'all'
Requires-Dist: pytest>=7.4.0; extra == 'all'
Requires-Dist: scikit-learn>=1.3.0; extra == 'all'
Requires-Dist: sphinx-rtd-theme>=1.3.0; extra == 'all'
Requires-Dist: sphinx>=7.0.0; extra == 'all'
Requires-Dist: tensorflow>=2.13.0; extra == 'all'
Requires-Dist: torch>=2.0.0; extra == 'all'
Provides-Extra: dev
Requires-Dist: black>=23.0.0; extra == 'dev'
Requires-Dist: flake8>=6.0.0; extra == 'dev'
Requires-Dist: isort>=5.12.0; extra == 'dev'
Requires-Dist: mypy>=1.5.0; extra == 'dev'
Requires-Dist: nbsphinx>=0.9.0; extra == 'dev'
Requires-Dist: pre-commit>=3.3.0; extra == 'dev'
Requires-Dist: pytest-benchmark>=4.0.0; extra == 'dev'
Requires-Dist: pytest-cov>=4.1.0; extra == 'dev'
Requires-Dist: pytest>=7.4.0; extra == 'dev'
Requires-Dist: sphinx-rtd-theme>=1.3.0; extra == 'dev'
Requires-Dist: sphinx>=7.0.0; extra == 'dev'
Provides-Extra: gpu
Requires-Dist: cupy-cuda12x>=12.0.0; extra == 'gpu'
Requires-Dist: numba[cuda]>=0.58.0; extra == 'gpu'
Provides-Extra: ml
Requires-Dist: optuna>=3.3.0; extra == 'ml'
Requires-Dist: scikit-learn>=1.3.0; extra == 'ml'
Requires-Dist: tensorflow>=2.13.0; extra == 'ml'
Requires-Dist: torch>=2.0.0; extra == 'ml'
